jwt_devices/__init__.py
jwt_devices/admin.py
jwt_devices/authentication.py
jwt_devices/middleware.py
jwt_devices/models.py
jwt_devices/serializers.py
jwt_devices/settings.py
jwt_devices/utils.py
jwt_devices/views.py
jwt_devices/migrations/0001_initial.py
jwt_devices/migrations/0002_auto_20181010_2152.py
jwt_devices/migrations/__init__.py
drf_jwt_devices-1.2.3.dist-info/LICENSE
drf_jwt_devices-1.2.3.dist-info/METADATA
drf_jwt_devices-1.2.3.dist-info/WHEEL
drf_jwt_devices-1.2.3.dist-info/top_level.txt
drf_jwt_devices-1.2.3.dist-info/RECORD
