Metadata-Version: 2.2
Name: drf-jwt-devices
Version: 1.2.3
Summary: Permanent token authentication for django-rest-framework-jwt
Home-page: https://github.com/HealthByRo/drf-jwt-devices
Author: Michal Proszek
Author-email: michalp@ro.co
License: MIT
Classifier: Development Status :: 7 - Inactive
Classifier: Environment :: Web Environment
Classifier: Framework :: Django
Classifier: Intended Audience :: Developers
Classifier: Operating System :: OS Independent
Classifier: Programming Language :: Python
Classifier: Programming Language :: Python :: 2.7
Classifier: Programming Language :: Python :: 3.4
Classifier: Programming Language :: Python :: 3.5
Classifier: Programming Language :: Python :: 3.6
Classifier: Topic :: Internet :: WWW/HTTP
License-File: LICENSE
Requires-Dist: djangorestframework-jwt>=1.11.0
Requires-Dist: six>=1.10.0
Dynamic: author
Dynamic: author-email
Dynamic: classifier
Dynamic: description
Dynamic: description-content-type
Dynamic: home-page
Dynamic: license
Dynamic: requires-dist
Dynamic: summary
